aioexos/__init__.py
aioexos/jsonrpc.py
aioexos/restconf.py
aio_exos-0.4.0.dist-info/LICENSE
aio_exos-0.4.0.dist-info/METADATA
aio_exos-0.4.0.dist-info/WHEEL
aio_exos-0.4.0.dist-info/top_level.txt
aio_exos-0.4.0.dist-info/RECORD
