Metadata-Version: 2.1
Name: aio-exos
Version: 0.4.0
Summary: Extreme EXOS asyncio client for JSON-RPC and RESTCONF
Home-page: UNKNOWN
Author: Jeremy Schulman
License: UNKNOWN
Platform: UNKNOWN
Classifier: Development Status :: 3 - Alpha
Classifier: Intended Audience :: Developers
Classifier: License :: OSI Approved :: Apache Software License
Classifier: Programming Language :: Python :: 3.8
Classifier: Topic :: Software Development :: Libraries :: Python Modules
Classifier: Topic :: System :: Networking
License-File: LICENSE
Requires-Dist: httpx
